{
  "source_database": {
    "database": "CV_DATA",
    "collection": "cv_berufsberatung",
    "total_documents": 1851,
    "sample_size": 0
  },
  "field_mapping": {
    "job_id": "id",
    "title": "name_de",
    "categories.berufsfelder": "berufsfeld",
    "categories.branchen": "branchen",
    "taetigkeiten.kategorien": "activities",
    "voraussetzungen.kategorisierte_anforderungen": "requirements",
    "weiterbildung.career_progression": "career_path",
    "categories.bildungstypen": "bildungstyp",
    "swissdoc": "swissdoc",
    "description": "description_de"
  },
  "industry_mapping": {
    "Bau": "construction",
    "Bau - Chemie, Physik": "construction",
    "Bau - Gebäudetechnik": "construction",
    "Bau - Gebäudetechnik - Elektrotechnik": "construction",
    "Bau - Holz, Innenausbau": "construction",
    "Bau - Natur": "construction",
    "Bau - Natur - Planung, Konstruktion": "construction",
    "Bau - Planung, Konstruktion": "construction",
    "Bau - Wirtschaft, Verwaltung, Tourismus": "finance",
    "Bildung, Soziales": "education",
    "Bildung, Soziales - Gesundheit": "technology",
    "Bildung, Soziales - Kultur, Medien": "education",
    "Bildung, Soziales - Natur": "education",
    "Chemie, Physik": "other",
    "Chemie, Physik - Metall, Maschinen, Uhren": "other",
    "Chemie, Physik - Nahrung": "other",
    "Chemie, Physik - Natur": "other",
    "Druck": "other",
    "Druck - Kultur, Medien": "other",
    "Druck - Wirtschaft, Verwaltung, Tourismus": "finance",
    "Elektrotechnik": "other",
    "Elektrotechnik - Bau": "construction",
    "Elektrotechnik - Informatik": "technology",
    "Elektrotechnik - Metall, Maschinen, Uhren": "other",
    "Elektrotechnik - Planung, Konstruktion": "other",
    "Fahrzeuge": "other",
    "Fahrzeuge - Chemie, Physik": "other",
    "Fahrzeuge - Holz, Innenausbau": "construction",
    "Fahrzeuge - Verkauf, Einkauf": "retail",
    "Fahrzeuge - Wirtschaft, Verwaltung, Tourismus": "finance",
    "Gastgewerbe, Hotellerie": "hospitality",
    "Gastgewerbe, Hotellerie - Gesundheit": "technology",
    "Gastgewerbe, Hotellerie - Wirtschaft, Verwaltung, Tourismus": "finance",
    "Gastgewerbe, Hotellerie - Wirtschaft, Verwaltung, Tourismus - Gebäudetechnik": "finance",
    "Gebäudetechnik": "other",
    "Gebäudetechnik - Planung, Konstruktion": "other",
    "Gebäudetechnik - Wirtschaft, Verwaltung, Tourismus": "finance",
    "Gestaltung, Kunsthandwerk": "other",
    "Gestaltung, Kunsthandwerk - Holz, Innenausbau": "construction",
    "Gestaltung, Kunsthandwerk - Informatik - Kultur, Medien": "technology",
    "Gestaltung, Kunsthandwerk - Kultur, Medien": "other",
    "Gestaltung, Kunsthandwerk - Verkauf, Einkauf": "retail",
    "Gesundheit": "technology",
    "Gesundheit - Bildung, Soziales": "technology",
    "Gesundheit - Chemie, Physik": "technology",
    "Gesundheit - Metall, Maschinen, Uhren - Elektrotechnik": "technology",
    "Gesundheit - Schönheit, Sport": "technology",
    "Holz, Innenausbau": "construction",
    "Holz, Innenausbau - Bau": "construction",
    "Holz, Innenausbau - Gestaltung, Kunsthandwerk": "construction",
    "Holz, Innenausbau - Verkauf, Einkauf": "construction",
    "Informatik": "technology",
    "Informatik - Elektrotechnik": "technology",
    "Kultur, Medien": "other",
    "Kultur, Medien - Bildung, Soziales": "education",
    "Kultur, Medien - Bildung, Soziales - Wirtschaft, Verwaltung, Tourismus": "finance",
    "Kultur, Medien - Gestaltung, Kunsthandwerk": "other",
    "Kultur, Medien - Planung, Konstruktion": "other",
    "Kultur, Medien - Wirtschaft, Verwaltung, Tourismus": "finance",
    "Metall, Maschinen, Uhren": "other",
    "Metall, Maschinen, Uhren - Chemie, Physik": "other",
    "Metall, Maschinen, Uhren - Elektrotechnik": "other",
    "Nahrung": "other",
    "Nahrung - Gesundheit": "technology",
    "Nahrung - Natur": "other",
    "Natur": "other",
    "Natur - Chemie, Physik": "other",
    "Natur - Elektrotechnik - Metall, Maschinen, Uhren": "other",
    "Natur - Gastgewerbe, Hotellerie": "hospitality",
    "Natur - Nahrung": "other",
    "Natur - Planung, Konstruktion": "other",
    "Natur - Wirtschaft, Verwaltung, Tourismus": "finance",
    "Planung, Konstruktion": "other",
    "Planung, Konstruktion - Bau": "construction",
    "Planung, Konstruktion - Elektrotechnik": "other",
    "Planung, Konstruktion - Gebäudetechnik": "other",
    "Planung, Konstruktion - Metall, Maschinen, Uhren": "other",
    "Planung, Konstruktion - Natur - Bau": "construction",
    "Schönheit, Sport": "technology",
    "Schönheit, Sport - Bildung, Soziales": "technology",
    "Schönheit, Sport - Gesundheit": "technology",
    "Schönheit, Sport - Natur": "technology",
    "Schönheit, Sport - Verkauf, Einkauf": "technology",
    "Schönheit, Sport - Wirtschaft, Verwaltung, Tourismus": "technology",
    "Textilien, Mode": "other",
    "Textilien, Mode - Fahrzeuge": "other",
    "Textilien, Mode - Gestaltung, Kunsthandwerk": "other",
    "Textilien, Mode - Holz, Innenausbau": "construction",
    "Textilien, Mode - Schönheit, Sport": "technology",
    "Verkauf, Einkauf": "retail",
    "Verkauf, Einkauf - Gesundheit": "technology",
    "Verkauf, Einkauf - Holz, Innenausbau": "construction",
    "Verkauf, Einkauf - Kultur, Medien": "retail",
    "Verkauf, Einkauf - Nahrung": "retail",
    "Verkauf, Einkauf - Verkehr, Logistik, Sicherheit": "technology",
    "Verkehr, Logistik, Sicherheit": "technology",
    "Verkehr, Logistik, Sicherheit - Gesundheit": "technology",
    "Verkehr, Logistik, Sicherheit - Wirtschaft, Verwaltung, Tourismus": "technology",
    "Wirtschaft, Verwaltung, Tourismus": "finance",
    "Wirtschaft, Verwaltung, Tourismus - Bildung, Soziales": "finance",
    "Wirtschaft, Verwaltung, Tourismus - Kultur, Medien": "finance",
    "Wirtschaft, Verwaltung, Tourismus - Verkehr, Logistik, Sicherheit - Bildung, Soziales": "technology",
    "Wirtschaft, Verwaltung, Tourismus - Verkehr, Logistik, Sicherheit - Metall, Maschinen, Uhren - Elektrotechnik - Chemie, Physik": "technology"
  },
  "data_structure": {
    "all_fields": [
      "_id",
      "apprenticeship_info",
      "ausbildung",
      "berufsverhaeltnisse",
      "categories",
      "data_completeness",
      "description",
      "extraction_timestamp",
      "extraction_version",
      "job_id",
      "taetigkeiten",
      "title",
      "url",
      "voraussetzungen",
      "weiterbildung",
      "weitere_informationen"
    ],
    "bildungstypen": [
      "Berufsfunktion / Spezialisierung",
      "Berufsfunktion / Spezialisierung - Hochschulberuf",
      "Berufsfunktion / Spezialisierung - Weiterbildungsberuf",
      "Grundbildung (Lehre)",
      "Hochschulberuf",
      "Hochschulberuf - Weiterbildungsberuf",
      "Weiterbildungsberuf"
    ],
    "berufsfelder": [
      "Bau",
      "Bau - Chemie, Physik",
      "Bau - Gebäudetechnik",
      "Bau - Gebäudetechnik - Elektrotechnik",
      "Bau - Holz, Innenausbau",
      "Bau - Natur",
      "Bau - Natur - Planung, Konstruktion",
      "Bau - Planung, Konstruktion",
      "Bau - Wirtschaft, Verwaltung, Tourismus",
      "Bildung, Soziales",
      "Bildung, Soziales - Gesundheit",
      "Bildung, Soziales - Kultur, Medien",
      "Bildung, Soziales - Natur",
      "Chemie, Physik",
      "Chemie, Physik - Metall, Maschinen, Uhren",
      "Chemie, Physik - Nahrung",
      "Chemie, Physik - Natur",
      "Druck",
      "Druck - Kultur, Medien",
      "Druck - Wirtschaft, Verwaltung, Tourismus",
      "Elektrotechnik",
      "Elektrotechnik - Bau",
      "Elektrotechnik - Informatik",
      "Elektrotechnik - Metall, Maschinen, Uhren",
      "Elektrotechnik - Planung, Konstruktion",
      "Fahrzeuge",
      "Fahrzeuge - Chemie, Physik",
      "Fahrzeuge - Holz, Innenausbau",
      "Fahrzeuge - Verkauf, Einkauf",
      "Fahrzeuge - Wirtschaft, Verwaltung, Tourismus",
      "Gastgewerbe, Hotellerie",
      "Gastgewerbe, Hotellerie - Gesundheit",
      "Gastgewerbe, Hotellerie - Wirtschaft, Verwaltung, Tourismus",
      "Gastgewerbe, Hotellerie - Wirtschaft, Verwaltung, Tourismus - Gebäudetechnik",
      "Gebäudetechnik",
      "Gebäudetechnik - Planung, Konstruktion",
      "Gebäudetechnik - Wirtschaft, Verwaltung, Tourismus",
      "Gestaltung, Kunsthandwerk",
      "Gestaltung, Kunsthandwerk - Holz, Innenausbau",
      "Gestaltung, Kunsthandwerk - Informatik - Kultur, Medien",
      "Gestaltung, Kunsthandwerk - Kultur, Medien",
      "Gestaltung, Kunsthandwerk - Verkauf, Einkauf",
      "Gesundheit",
      "Gesundheit - Bildung, Soziales",
      "Gesundheit - Chemie, Physik",
      "Gesundheit - Metall, Maschinen, Uhren - Elektrotechnik",
      "Gesundheit - Schönheit, Sport",
      "Holz, Innenausbau",
      "Holz, Innenausbau - Bau",
      "Holz, Innenausbau - Gestaltung, Kunsthandwerk",
      "Holz, Innenausbau - Verkauf, Einkauf",
      "Informatik",
      "Informatik - Elektrotechnik",
      "Kultur, Medien",
      "Kultur, Medien - Bildung, Soziales",
      "Kultur, Medien - Bildung, Soziales - Wirtschaft, Verwaltung, Tourismus",
      "Kultur, Medien - Gestaltung, Kunsthandwerk",
      "Kultur, Medien - Planung, Konstruktion",
      "Kultur, Medien - Wirtschaft, Verwaltung, Tourismus",
      "Metall, Maschinen, Uhren",
      "Metall, Maschinen, Uhren - Chemie, Physik",
      "Metall, Maschinen, Uhren - Elektrotechnik",
      "Nahrung",
      "Nahrung - Gesundheit",
      "Nahrung - Natur",
      "Natur",
      "Natur - Chemie, Physik",
      "Natur - Elektrotechnik - Metall, Maschinen, Uhren",
      "Natur - Gastgewerbe, Hotellerie",
      "Natur - Nahrung",
      "Natur - Planung, Konstruktion",
      "Natur - Wirtschaft, Verwaltung, Tourismus",
      "Planung, Konstruktion",
      "Planung, Konstruktion - Bau",
      "Planung, Konstruktion - Elektrotechnik",
      "Planung, Konstruktion - Gebäudetechnik",
      "Planung, Konstruktion - Metall, Maschinen, Uhren",
      "Planung, Konstruktion - Natur - Bau",
      "Schönheit, Sport",
      "Schönheit, Sport - Bildung, Soziales",
      "Schönheit, Sport - Gesundheit",
      "Schönheit, Sport - Natur",
      "Schönheit, Sport - Verkauf, Einkauf",
      "Schönheit, Sport - Wirtschaft, Verwaltung, Tourismus",
      "Textilien, Mode",
      "Textilien, Mode - Fahrzeuge",
      "Textilien, Mode - Gestaltung, Kunsthandwerk",
      "Textilien, Mode - Holz, Innenausbau",
      "Textilien, Mode - Schönheit, Sport",
      "Verkauf, Einkauf",
      "Verkauf, Einkauf - Gesundheit",
      "Verkauf, Einkauf - Holz, Innenausbau",
      "Verkauf, Einkauf - Kultur, Medien",
      "Verkauf, Einkauf - Nahrung",
      "Verkauf, Einkauf - Verkehr, Logistik, Sicherheit",
      "Verkehr, Logistik, Sicherheit",
      "Verkehr, Logistik, Sicherheit - Gesundheit",
      "Verkehr, Logistik, Sicherheit - Wirtschaft, Verwaltung, Tourismus",
      "Wirtschaft, Verwaltung, Tourismus",
      "Wirtschaft, Verwaltung, Tourismus - Bildung, Soziales",
      "Wirtschaft, Verwaltung, Tourismus - Kultur, Medien",
      "Wirtschaft, Verwaltung, Tourismus - Verkehr, Logistik, Sicherheit - Bildung, Soziales",
      "Wirtschaft, Verwaltung, Tourismus - Verkehr, Logistik, Sicherheit - Metall, Maschinen, Uhren - Elektrotechnik - Chemie, Physik"
    ]
  },
  "field_completeness": {
    "_id": 54.02,
    "url": 54.02,
    "apprenticeship_info": 54.02,
    "ausbildung": 54.02,
    "berufsverhaeltnisse": 54.02,
    "categories": 54.02,
    "data_completeness": 54.02,
    "extraction_timestamp": 54.02,
    "extraction_version": 54.02,
    "job_id": 54.02,
    "taetigkeiten": 54.02,
    "title": 54.02,
    "voraussetzungen": 54.02,
    "weiterbildung": 54.02,
    "weitere_informationen": 54.02,
    "description": 28.36
  }
}